{
	"id": "f7624f1d-60c7-405b-9add-07b547b2f5a9",
	"name": "boards",
	"values": [
		{
			"key": "boards_base_url",
			"value": "https://api.trello.com",
			"type": "default",
			"enabled": true
		},
		{
			"key": "api_key",
			"value": "96f40d4c4ebe28d555231a8eec223a1d",
			"type": "default",
			"enabled": true
		},
		{
			"key": "api_token",
			"value": "ATTAfb4bc289f10c5a46dce832718f7e00dcc08c36e65998d0e5deb34dde3648f9c35C5FB7FB",
			"type": "default",
			"enabled": true
		},
		{
			"key": "crt_board_name",
			"value": "Mohana's",
			"type": "default",
			"enabled": true
		},
		{
			"key": "mohana_id",
			"value": "",
			"type": "any",
			"enabled": true
		},
		{
			"key": "update_name",
			"value": "Kasi's",
			"type": "default",
			"enabled": true
		},
		{
			"key": "color",
			"value": "purple",
			"type": "default",
			"enabled": true
		}
	],
	"_postman_variable_scope": "environment",
	"_postman_exported_at": "2023-12-03T07:15:07.296Z",
	"_postman_exported_using": "Postman/10.20.0"
}